mp_pytorch/__init__.py
mp_pytorch/basis_gn/__init__.py
mp_pytorch/basis_gn/basis_generator.py
mp_pytorch/basis_gn/norm_rbf_basis.py
mp_pytorch/basis_gn/prodmp_basis.py
mp_pytorch/basis_gn/rhytmic_basis.py
mp_pytorch/demo/__init__.py
mp_pytorch/demo/demo_basis_gn.py
mp_pytorch/demo/demo_data_type_cast.py
mp_pytorch/demo/demo_delay_and_scale.py
mp_pytorch/demo/demo_dmp.py
mp_pytorch/demo/demo_mp_config.py
mp_pytorch/demo/demo_prodmp.py
mp_pytorch/demo/demo_prodmp_autoscale.py
mp_pytorch/demo/demo_promp.py
mp_pytorch/mp/__init__.py
mp_pytorch/mp/dmp.py
mp_pytorch/mp/mp_factory.py
mp_pytorch/mp/mp_interfaces.py
mp_pytorch/mp/prodmp.py
mp_pytorch/mp/promp.py
mp_pytorch/phase_gn/__init__.py
mp_pytorch/phase_gn/exp_decay_phase.py
mp_pytorch/phase_gn/linear_phase.py
mp_pytorch/phase_gn/phase_generator.py
mp_pytorch/phase_gn/rhythmic_phase_generator.py
mp_pytorch/phase_gn/smooth_phase_generator.py
mp_pytorch/util/__init__.py
mp_pytorch/util/util_data_structure.py
mp_pytorch/util/util_debug.py
mp_pytorch/util/util_matrix.py
mp_pytorch/util/util_media.py
mp_pytorch/util/util_string.py
mp_pytorch-0.1.4.dist-info/LICENSE
mp_pytorch-0.1.4.dist-info/METADATA
mp_pytorch-0.1.4.dist-info/WHEEL
mp_pytorch-0.1.4.dist-info/top_level.txt
mp_pytorch-0.1.4.dist-info/RECORD
