Metadata-Version: 2.1
Name: mp_pytorch
Version: 0.1.4
Summary: The Movement Primitives Package in PyTorch
Home-page: https://github.com/ALRhub/MP_PyTorch
Author: Ge Li @ ALR, KIT
Author-email: ge.li@kit.edu
License: MIT
Classifier: Intended Audience :: Science/Research
Classifier: Programming Language :: Python :: 3
Classifier: License :: OSI Approved :: MIT License
Classifier: Operating System :: POSIX :: Linux
License-File: LICENSE
